{
  "SceneObj_Area_Common_Property_Prop_EmptyFloraShelve_01": {
    "$type": "DIPBMCMACLG",
    "NMPCLILNJBG": true,
    "combat": {
      "property": {
        "HP": 99999.0,
        "isLockHP": true,
        "ignoreDamageToSelf": true
      }
    },
    "combatTemplate": "",
    "FJFLNHEEMPP": {
      "ILPABHHNHHH": "UI/open_custom_gadget_page",
      "NKDDMFJGNAM": "UI_HOMEWORLD_CUSTOM_BUTTON",
      "icon": "",
      "HKEDHENAABH": "",
      "GOJGHFJHCGM": "",
      "DLAEFBONFEI": "",
      "CLGACEGICGN": false
    },
    "AMMPPPJAAIJ": {
      "KOLEDCFELBO": {
        "GKDKHBPFGOD": {
          "BBMHMFOANHL": 1.7000000476837158
        },
        "slotMap": {
          "FlowerShelf": {
            "KKDHMFLLBEF": "FlowerShelf",
            "LCPIBPAHKID": 1000
          }
        }
      },
      "EBEAJEMNNAN": ""
    },
    "DIHIOMAKNFI": {
      "DBMEAJCPMBM": 3.0
    }
  },
  "SceneObj_Area_Common_Property_Prop_SnowmanBody_01": {
    "$type": "DIPBMCMACLG",
    "NMPCLILNJBG": true,
    "combat": {
      "property": {
        "HP": 99999.0,
        "isLockHP": true,
        "ignoreDamageToSelf": true
      }
    },
    "combatTemplate": "",
    "FJFLNHEEMPP": {
      "ILPABHHNHHH": "UI/open_custom_gadget_page",
      "NKDDMFJGNAM": "UI_HOMEWORLD_CUSTOM_SNOWMANBUTTON",
      "icon": "",
      "HKEDHENAABH": "",
      "GOJGHFJHCGM": "",
      "DLAEFBONFEI": "",
      "CLGACEGICGN": false
    },
    "AMMPPPJAAIJ": {
      "KOLEDCFELBO": {
        "GKDKHBPFGOD": {
          "BBMHMFOANHL": 1.7000000476837158
        },
        "slotMap": {
          "Head": {
            "KKDHMFLLBEF": "Head",
            "LCPIBPAHKID": 11
          },
          "Hand": {
            "KKDHMFLLBEF": "Hand",
            "LCPIBPAHKID": 12
          }
        }
      },
      "EBEAJEMNNAN": ""
    },
    "DIHIOMAKNFI": {
      "DBMEAJCPMBM": 3.0
    }
  },
  "SceneObj_Area_Dq_Property_Prop_Irodori_Miniascape_01": {
    "$type": "DIPBMCMACLG",
    "NMPCLILNJBG": true,
    "combat": {
      "property": {
        "HP": 99999.0,
        "isLockHP": true,
        "ignoreDamageToSelf": true
      }
    },
    "combatTemplate": "",
    "FJFLNHEEMPP": {
      "ILPABHHNHHH": "UI/open_custom_gadget_page",
      "NKDDMFJGNAM": "UI_HOMEWORLD_CUSTOM_MINIASCAPE",
      "icon": "",
      "HKEDHENAABH": "",
      "GOJGHFJHCGM": "",
      "DLAEFBONFEI": "",
      "CLGACEGICGN": false
    },
    "AMMPPPJAAIJ": {
      "KOLEDCFELBO": {
        "GKDKHBPFGOD": {
          "BBMHMFOANHL": 0.800000011920929
        },
        "slotMap": {
          "FrontScene": {
            "KKDHMFLLBEF": "FrontScene",
            "LCPIBPAHKID": 21
          },
          "BehindScene": {
            "KKDHMFLLBEF": "BehindScene",
            "LCPIBPAHKID": 22
          }
        }
      },
      "EBEAJEMNNAN": ""
    },
    "DIHIOMAKNFI": {
      "EHOACOBIOGM": 1.2000000476837158,
      "DBMEAJCPMBM": 3.0
    }
  },
  "SceneObj_Area_Xm_Property_Prop_WoodAranaraStage_Slot_01": {
    "$type": "DIPBMCMACLG",
    "NMPCLILNJBG": true,
    "combat": {
      "property": {
        "HP": 99999.0,
        "isLockHP": true,
        "ignoreDamageToSelf": true
      }
    },
    "combatTemplate": "",
    "abilities": [
      {
        "abilityID": "SceneObj_Area_Xm_Property_Prop_WoodAranaraStage_Slot_01",
        "abilityName": "SceneObj_Area_Xm_Property_Prop_WoodAranaraStage_Slot_01",
        "abilityOverride": ""
      }
    ],
    "FJFLNHEEMPP": {
      "ILPABHHNHHH": "UI/open_custom_gadget_page",
      "NKDDMFJGNAM": "",
      "IDJCICEIBHF": [
        "HOST"
      ],
      "icon": "",
      "HKEDHENAABH": "",
      "GOJGHFJHCGM": "",
      "DLAEFBONFEI": "",
      "CLGACEGICGN": false
    },
    "AMMPPPJAAIJ": {
      "KOLEDCFELBO": {
        "GKDKHBPFGOD": {},
        "slotMap": {
          "Body": {
            "KKDHMFLLBEF": "Body",
            "LCPIBPAHKID": 1001
          }
        }
      },
      "EBEAJEMNNAN": ""
    },
    "DIHIOMAKNFI": {
      "EHOACOBIOGM": 1.5,
      "DBMEAJCPMBM": 3.0
    }
  }
}
