{
  "Klee_NormalAttack": {
    "$type": "DIPBMCMACLG",
    "common": {
      "effectAttachShape": {
        "$type": "GGMDGIIFNHF",
        "OGNCHCNHLAO": 0.4000000059604645
      },
      "mass": 5.0,
      "affectedByWorld": true,
      "checkInSurface": true
    },
    "combat": {
      "property": {
        "useCreatorProperty": true,
        "HP": 99999.0,
        "isLockHP": true,
        "isGhostToAllied": true
      },
      "combatLock": {
        "lockShape": "CircleLockEnemy",
        "denyLockOn": true,
        "lockType": "Gadget_Lv1"
      }
    },
    "combatTemplate": "",
    "abilities": [
      {
        "abilityID": "NoarmalAttack_Damage",
        "abilityName": "Avatar_Klee_NoarmalAttack_01_Damage",
        "abilityOverride": ""
      },
      {
        "abilityID": "Material",
        "abilityName": "Avatar_Klee_Attack01_Material",
        "abilityOverride": ""
      }
    ],
    "DIKDGEMENBA": {
      "lifeTime": 2.0
    },
    "move": {
      "$type": "DCKFCEDKLMB",
      "speed": 20.0,
      "BINOLELMLBN": 25.0,
      "OEMLEAMBOPG": 40.0,
      "LOFMGNMHPCI": {
        "$type": "LACOOICJPNO",
        "GOKDDFINCGA": 15.0,
        "minSpeed": 4.0,
        "maxSpeed": 18.0
      }
    },
    "EHLHLJKBBBN": {
      "$type": "CBHLADGGJNA",
      "collision": {
        "targetType": "Enemy"
      },
      "EJIHDAJIDGP": [
        {
          "$type": "FPMCAJNLEEK",
          "abilityName": "Avatar_Klee_NoarmalAttack_01_Damage"
        }
      ]
    }
  },
  "Klee_NormalAttack_02": {
    "$type": "DIPBMCMACLG",
    "common": {
      "effectAttachShape": {
        "$type": "GGMDGIIFNHF",
        "OGNCHCNHLAO": 0.4000000059604645
      },
      "mass": 5.0,
      "affectedByWorld": true,
      "checkInSurface": true
    },
    "combat": {
      "property": {
        "useCreatorProperty": true,
        "HP": 99999.0,
        "isLockHP": true,
        "isGhostToAllied": true
      },
      "combatLock": {
        "lockShape": "CircleLockEnemy",
        "denyLockOn": true,
        "lockType": "Gadget_Lv1"
      }
    },
    "combatTemplate": "",
    "abilities": [
      {
        "abilityID": "NoarmalAttack_Damage",
        "abilityName": "Avatar_Klee_NoarmalAttack_02_Damage",
        "abilityOverride": ""
      },
      {
        "abilityID": "Material",
        "abilityName": "Avatar_Klee_Attack01_Material",
        "abilityOverride": ""
      }
    ],
    "DIKDGEMENBA": {
      "lifeTime": 2.0
    },
    "move": {
      "$type": "DCKFCEDKLMB",
      "speed": 20.0,
      "BINOLELMLBN": 25.0,
      "OEMLEAMBOPG": 40.0,
      "LOFMGNMHPCI": {
        "$type": "LACOOICJPNO",
        "GOKDDFINCGA": 15.0,
        "minSpeed": 4.0,
        "maxSpeed": 18.0
      }
    },
    "EHLHLJKBBBN": {
      "$type": "CBHLADGGJNA",
      "collision": {
        "targetType": "Enemy"
      },
      "EJIHDAJIDGP": [
        {
          "$type": "FPMCAJNLEEK",
          "abilityName": "Avatar_Klee_NoarmalAttack_02_Damage"
        }
      ]
    }
  },
  "Klee_NormalAttack_03": {
    "$type": "DIPBMCMACLG",
    "common": {
      "effectAttachShape": {
        "$type": "GGMDGIIFNHF",
        "OGNCHCNHLAO": 0.4000000059604645
      },
      "mass": 5.0,
      "affectedByWorld": true,
      "checkInSurface": true
    },
    "combat": {
      "property": {
        "useCreatorProperty": true,
        "HP": 99999.0,
        "isLockHP": true,
        "isGhostToAllied": true
      },
      "combatLock": {
        "lockShape": "CircleLockEnemy",
        "denyLockOn": true,
        "lockType": "Gadget_Lv1"
      }
    },
    "combatTemplate": "",
    "abilities": [
      {
        "abilityID": "NoarmalAttack_Damage",
        "abilityName": "Avatar_Klee_NoarmalAttack_03_Damage",
        "abilityOverride": ""
      },
      {
        "abilityID": "Material",
        "abilityName": "Avatar_Klee_Attack03_Material",
        "abilityOverride": ""
      }
    ],
    "DIKDGEMENBA": {
      "lifeTime": 2.0
    },
    "move": {
      "$type": "DCKFCEDKLMB",
      "speed": 20.0,
      "BINOLELMLBN": 25.0,
      "OEMLEAMBOPG": 40.0,
      "LOFMGNMHPCI": {
        "$type": "LACOOICJPNO",
        "GOKDDFINCGA": 15.0,
        "minSpeed": 4.0,
        "maxSpeed": 18.0
      }
    },
    "EHLHLJKBBBN": {
      "$type": "CBHLADGGJNA",
      "collision": {
        "targetType": "Enemy"
      },
      "EJIHDAJIDGP": [
        {
          "$type": "FPMCAJNLEEK",
          "abilityName": "Avatar_Klee_NoarmalAttack_03_Damage"
        }
      ]
    }
  },
  "Klee_JumpBomb_01": {
    "$type": "DIPBMCMACLG",
    "common": {
      "effectAttachShape": {
        "$type": "GGMDGIIFNHF",
        "OGNCHCNHLAO": 0.4000000059604645
      },
      "mass": 5.0,
      "affectedByWorld": true,
      "checkInSurface": true
    },
    "combat": {
      "property": {
        "useCreatorProperty": true,
        "HP": 99999.0,
        "isLockHP": true,
        "isGhostToAllied": true
      },
      "combatLock": {
        "lockShape": "CircleLockEnemy",
        "denyLockOn": true,
        "lockType": "Gadget_Lv1"
      }
    },
    "combatTemplate": "",
    "abilities": [
      {
        "abilityID": "Bomb_Explode1",
        "abilityName": "Jumping_Drug_Explode",
        "abilityOverride": ""
      }
    ],
    "DIKDGEMENBA": {
      "lifeTime": 10.0
    },
    "move": {
      "$type": "DCKFCEDKLMB",
      "speed": 8.0,
      "CPOHOLCJKDA": 0.029999999329447746,
      "BINOLELMLBN": 40.0,
      "OEMLEAMBOPG": 30.0,
      "LOFMGNMHPCI": {
        "$type": "LACOOICJPNO",
        "DAAPENDKNKE": 0.5,
        "GOKDDFINCGA": 5.0,
        "minSpeed": 8.0,
        "maxSpeed": 9.0
      }
    },
    "EHLHLJKBBBN": {
      "$type": "CBHLADGGJNA",
      "collision": {},
      "EJIHDAJIDGP": [
        {
          "$type": "FPMCAJNLEEK",
          "abilityName": "Jumping_Drug_Explode"
        }
      ]
    }
  },
  "Klee_JumpBomb_02": {
    "$type": "DIPBMCMACLG",
    "common": {
      "effectAttachShape": {
        "$type": "GGMDGIIFNHF",
        "OGNCHCNHLAO": 0.4000000059604645
      },
      "mass": 5.0,
      "affectedByWorld": true,
      "checkInSurface": true
    },
    "combat": {
      "property": {
        "useCreatorProperty": true,
        "HP": 99999.0,
        "isLockHP": true,
        "isGhostToAllied": true
      },
      "combatLock": {
        "lockShape": "CircleLockEnemy",
        "denyLockOn": true,
        "lockType": "Gadget_Lv1"
      }
    },
    "combatTemplate": "",
    "abilities": [
      {
        "abilityID": "Bomb_Explode2",
        "abilityName": "Jumping_Drug_Explode2",
        "abilityOverride": ""
      }
    ],
    "DIKDGEMENBA": {
      "lifeTime": 10.0
    },
    "move": {
      "$type": "DCKFCEDKLMB",
      "speed": 8.0,
      "CPOHOLCJKDA": 0.10000000149011612,
      "BINOLELMLBN": 70.0,
      "OEMLEAMBOPG": 30.0,
      "LOFMGNMHPCI": {
        "$type": "LACOOICJPNO",
        "DAAPENDKNKE": 0.07999999821186066,
        "GOKDDFINCGA": 5.0,
        "minSpeed": 8.0,
        "maxSpeed": 9.0
      }
    },
    "EHLHLJKBBBN": {
      "$type": "CBHLADGGJNA",
      "collision": {
        "targetType": "Enemy",
        "bornWithTriggerEnabled": false
      },
      "EJIHDAJIDGP": [
        {
          "$type": "FPMCAJNLEEK",
          "abilityName": "Jumping_Drug_Explode2"
        }
      ],
      "AHCHIHHNLEF": 0.30000001192092896
    }
  },
  "Klee_JumpBomb_03": {
    "$type": "DIPBMCMACLG",
    "common": {
      "effectAttachShape": {
        "$type": "GGMDGIIFNHF",
        "OGNCHCNHLAO": 0.4000000059604645
      },
      "mass": 5.0,
      "affectedByWorld": true,
      "checkInSurface": true
    },
    "combat": {
      "property": {
        "useCreatorProperty": true,
        "HP": 99999.0,
        "isLockHP": true,
        "isGhostToAllied": true
      },
      "combatLock": {
        "lockShape": "CircleLockEnemy",
        "denyLockOn": true,
        "lockType": "Gadget_Lv1"
      }
    },
    "combatTemplate": "",
    "abilities": [
      {
        "abilityID": "Bomb_Explode3",
        "abilityName": "Jumping_Drug_Explode3",
        "abilityOverride": ""
      }
    ],
    "DIKDGEMENBA": {
      "lifeTime": 10.0
    },
    "move": {
      "$type": "DCKFCEDKLMB",
      "speed": 8.0,
      "CPOHOLCJKDA": 0.10000000149011612,
      "BINOLELMLBN": 70.0,
      "OEMLEAMBOPG": 30.0,
      "LOFMGNMHPCI": {
        "$type": "LACOOICJPNO",
        "DAAPENDKNKE": 0.5,
        "GOKDDFINCGA": 5.0,
        "minSpeed": 8.0,
        "maxSpeed": 9.0
      }
    },
    "EHLHLJKBBBN": {
      "$type": "CBHLADGGJNA",
      "collision": {
        "targetType": "Enemy",
        "bornWithTriggerEnabled": false
      },
      "EJIHDAJIDGP": [
        {
          "$type": "FPMCAJNLEEK",
          "abilityName": "Jumping_Drug_Explode3"
        }
      ],
      "AHCHIHHNLEF": 0.30000001192092896
    }
  },
  "JumpDrug_Whitbox_04": {
    "$type": "DIPBMCMACLG",
    "common": {
      "effectAttachShape": {
        "$type": "GGMDGIIFNHF",
        "OGNCHCNHLAO": 0.4000000059604645
      },
      "mass": 5.0,
      "affectedByWorld": true,
      "checkInSurface": true
    },
    "combat": {
      "property": {
        "useCreatorProperty": true,
        "HP": 99999.0,
        "isLockHP": true,
        "isGhostToAllied": true
      },
      "combatLock": {
        "lockShape": "CircleLockEnemy",
        "denyLockOn": true,
        "lockType": "Gadget_Lv1"
      }
    },
    "combatTemplate": "",
    "DIKDGEMENBA": {
      "lifeTime": 15.0
    },
    "move": {
      "$type": "DCKFCEDKLMB",
      "speed": 10.0,
      "BINOLELMLBN": 25.0,
      "OEMLEAMBOPG": 12.0,
      "LOFMGNMHPCI": {
        "$type": "LACOOICJPNO",
        "DAAPENDKNKE": 2.0,
        "GOKDDFINCGA": 5.0,
        "minSpeed": 5.0,
        "maxSpeed": 20.0
      }
    },
    "EHLHLJKBBBN": {
      "$type": "CBHLADGGJNA",
      "collision": {
        "targetType": "Enemy"
      }
    },
    "NGDLOOAIHKB": {
      "OJOEAEDPNCE": "equip03",
      "NGLDDCMDHBN": "",
      "GOLPLOGIGJA": "",
      "MGHNJAFCNCF": "Spear"
    }
  },
  "Klee_Mine_Throw": {
    "$type": "DIPBMCMACLG",
    "common": {
      "effectAttachShape": {
        "$type": "GGMDGIIFNHF",
        "OGNCHCNHLAO": 0.4000000059604645
      },
      "mass": 5.0,
      "affectedByWorld": true,
      "checkInSurface": true
    },
    "combat": {
      "property": {
        "useCreatorProperty": true,
        "isLockHP": true,
        "isGhostToAllied": true
      },
      "combatLock": {
        "lockShape": "CircleLockEnemy",
        "denyLockOn": true,
        "lockType": "Gadget_Lv1"
      }
    },
    "combatTemplate": "",
    "abilities": [
      {
        "abilityID": "Avatar_Klee_ThrowMine",
        "abilityName": "Avatar_Klee_ThrowMine",
        "abilityOverride": ""
      }
    ],
    "DIKDGEMENBA": {
      "lifeTime": 5.0
    },
    "move": {
      "$type": "DCKFCEDKLMB",
      "speed": 12.0,
      "AOHCALMCNHB": -10.0,
      "BINOLELMLBN": 70.0,
      "OEMLEAMBOPG": 35.0
    },
    "EHLHLJKBBBN": {
      "$type": "CBHLADGGJNA",
      "collision": {
        "targetType": "Enemy",
        "bornWithTriggerEnabled": false
      },
      "EJIHDAJIDGP": [
        {
          "$type": "FPMCAJNLEEK",
          "abilityName": "Avatar_Klee_ThrowMine"
        }
      ],
      "AHCHIHHNLEF": 0.20000000298023224
    }
  },
  "Avatar_Klee_Mine": {
    "$type": "DIPBMCMACLG",
    "common": {
      "effectAttachShape": {
        "$type": "GGMDGIIFNHF"
      },
      "affectedByWorld": true
    },
    "combat": {
      "property": {
        "useCreatorProperty": true
      },
      "beHit": {
        "hitBloodEffect": "",
        "muteAllHitText": true
      },
      "combatLock": {
        "lockShape": "CircleLockEnemy",
        "denyLockOn": true,
        "lockType": "Gadget_Lv1"
      }
    },
    "combatTemplate": "",
    "abilities": [
      {
        "abilityID": "Avatar_Klee_Mine",
        "abilityName": "Avatar_Klee_Mine",
        "abilityOverride": ""
      },
      {
        "abilityID": "Avatar_Klee_Constellation_2",
        "abilityName": "Avatar_Klee_Constellation_2",
        "abilityOverride": ""
      }
    ],
    "DIKDGEMENBA": {
      "lifeTime": 16.0
    },
    "move": {
      "$type": "KAMMICAEPJI",
      "LJOOJNLJPDM": {
        "includeForces": [
          "WindZoneType",
          "RetreatType",
          "RetreatAirType"
        ]
      },
      "FLEBENBODEA": false
    },
    "EHLHLJKBBBN": {
      "$type": "CBHLADGGJNA",
      "collision": {
        "targetType": "Enemy",
        "ignoreScene": true
      },
      "EJIHDAJIDGP": [
        {
          "$type": "FPMCAJNLEEK",
          "abilityName": "Avatar_Klee_Mine"
        }
      ],
      "AHCHIHHNLEF": 1.0,
      "CBPMAPDNDLJ": true,
      "IFCHDOBJDHL": true
    }
  },
  "Klee_Elemental_Burst_Trigger": {
    "$type": "DIPBMCMACLG",
    "common": {
      "effectAttachShape": {
        "$type": "GGMDGIIFNHF"
      }
    },
    "combat": {
      "property": {
        "useCreatorProperty": true,
        "isGhostToEnemy": true
      }
    },
    "combatTemplate": "",
    "abilities": [
      {
        "abilityID": "CreateBomb",
        "abilityName": "Avatar_Klee_Elemental_Burst_Trigger",
        "abilityOverride": ""
      }
    ],
    "DIKDGEMENBA": {
      "lifeTime": 25.0
    },
    "move": {
      "$type": "BLMOMLOKBPD",
      "attachPoint": "",
      "followRotation": true,
      "offset": {
        "y": 1.0
      },
      "DHNALNHBGHF": true,
      "NDKPBDKKOKB": ""
    }
  },
  "Klee_Elemental_Burst_Bomb": {
    "$type": "DIPBMCMACLG",
    "combat": {
      "property": {
        "useCreatorProperty": true,
        "weight": 50.0,
        "isGhostToAllied": true,
        "isGhostToEnemy": true
      },
      "beHit": {
        "hitBloodEffect": "",
        "IPPKADMAEPO": true,
        "muteAllHitEffect": true,
        "muteAllHitText": true
      },
      "combatLock": {
        "lockShape": "CircleLockEnemy",
        "denyLockOn": true,
        "lockType": "Gadget_Lv1"
      }
    },
    "combatTemplate": "",
    "abilities": [
      {
        "abilityID": "Explode",
        "abilityName": "Avatar_Klee_Elemental_Burst_Explode",
        "abilityOverride": ""
      }
    ],
    "DIKDGEMENBA": {
      "lifeTime": 2.0
    },
    "move": {
      "$type": "DCNGIEDOJBG",
      "speed": 25.0,
      "maxSpeed": 25.0,
      "minSpeed": 20.0,
      "AOHCALMCNHB": 1.0,
      "ELPIEGMDKFC": true
    },
    "EHLHLJKBBBN": {
      "$type": "CBHLADGGJNA",
      "collision": {
        "targetType": "Enemy"
      },
      "EJIHDAJIDGP": [
        {
          "$type": "FPMCAJNLEEK",
          "abilityName": "Avatar_Klee_Elemental_Burst_Explode"
        }
      ]
    }
  },
  "Klee_Constellation_Bomb": {
    "$type": "DIPBMCMACLG",
    "combat": {
      "property": {
        "useCreatorProperty": true,
        "weight": 50.0,
        "isGhostToAllied": true,
        "isGhostToEnemy": true
      },
      "beHit": {
        "hitBloodEffect": "",
        "IPPKADMAEPO": true,
        "muteAllHitEffect": true,
        "muteAllHitText": true
      },
      "combatLock": {
        "lockShape": "CircleLockEnemy",
        "denyLockOn": true,
        "lockType": "Gadget_Lv1"
      }
    },
    "combatTemplate": "",
    "abilities": [
      {
        "abilityID": "Explode",
        "abilityName": "Avatar_Klee_Constellation_Explode",
        "abilityOverride": ""
      }
    ],
    "DIKDGEMENBA": {
      "lifeTime": 2.0
    },
    "move": {
      "$type": "DCNGIEDOJBG",
      "speed": 25.0,
      "maxSpeed": 25.0,
      "minSpeed": 20.0,
      "AOHCALMCNHB": 1.0,
      "ELPIEGMDKFC": true
    },
    "EHLHLJKBBBN": {
      "$type": "CBHLADGGJNA",
      "collision": {
        "targetType": "Enemy"
      },
      "EJIHDAJIDGP": [
        {
          "$type": "FPMCAJNLEEK",
          "abilityName": "Avatar_Klee_Constellation_Explode"
        }
      ]
    }
  },
  "Klee_Elemental_Burst_Funnel": {
    "$type": "DIPBMCMACLG",
    "common": {
      "effectAttachShape": {
        "$type": "GGMDGIIFNHF"
      },
      "affectedByWorld": true,
      "checkInSurface": true
    },
    "combat": {
      "property": {
        "useCreatorProperty": true,
        "weight": 150.0,
        "isInvincible": true
      },
      "combatLock": {
        "lockShape": "CircleLockEnemy",
        "denyLockOn": true,
        "lockType": "Gadget_Lv1"
      },
      "die": {
        "dieDisappearEffect": ""
      }
    },
    "combatTemplate": "",
    "abilities": [
      {
        "abilityID": "Funnel",
        "abilityName": "Klee_Elemental_Burst_Funnel",
        "abilityOverride": ""
      }
    ],
    "DIKDGEMENBA": {
      "lifeTime": 1.5
    },
    "move": {
      "$type": "DCNGIEDOJBG",
      "speed": 0.009999999776482582,
      "DFFLBAEENFC": {
        "$type": "BDKHNGDHLBP",
        "JIHELKPDKHN": 360.0
      },
      "ELPIEGMDKFC": true
    }
  },
  "Klee_Constellation_Funnel": {
    "$type": "DIPBMCMACLG",
    "common": {
      "effectAttachShape": {
        "$type": "GGMDGIIFNHF"
      },
      "affectedByWorld": true,
      "checkInSurface": true
    },
    "combat": {
      "property": {
        "useCreatorProperty": true,
        "weight": 150.0,
        "isInvincible": true
      },
      "combatLock": {
        "lockShape": "CircleLockEnemy",
        "denyLockOn": true,
        "lockType": "Gadget_Lv1"
      },
      "die": {
        "dieDisappearEffect": ""
      }
    },
    "combatTemplate": "",
    "abilities": [
      {
        "abilityID": "Constellation_Funnel",
        "abilityName": "Klee_Constellation_Funnel",
        "abilityOverride": ""
      }
    ],
    "DIKDGEMENBA": {
      "lifeTime": 1.5
    },
    "move": {
      "$type": "DCNGIEDOJBG",
      "speed": 0.009999999776482582,
      "DFFLBAEENFC": {
        "$type": "BDKHNGDHLBP",
        "JIHELKPDKHN": 360.0
      },
      "ELPIEGMDKFC": true
    }
  },
  "Klee_Elemental_Burst_Bullet": {
    "$type": "DIPBMCMACLG",
    "common": {
      "effectAttachShape": {
        "$type": "GGMDGIIFNHF"
      }
    },
    "combat": {
      "property": {
        "useCreatorProperty": true,
        "isGhostToAllied": true,
        "isGhostToEnemy": true,
        "MBEICKDJMFI": false
      },
      "beHit": {
        "hitBloodEffect": "",
        "IPPKADMAEPO": true,
        "muteAllHitEffect": true,
        "muteAllHitText": true
      },
      "combatLock": {
        "lockShape": "CircleLockEnemy",
        "denyLockOn": true,
        "lockType": "Gadget_Lv1"
      }
    },
    "combatTemplate": "",
    "abilities": [
      {
        "abilityID": "CreateFunnel",
        "abilityName": "Avatar_Klee_ElementalBurst_CreateFunnel",
        "abilityOverride": ""
      },
      {
        "abilityID": "Material",
        "abilityName": "Avatar_Klee_ElementalBurst_Bullet_Material",
        "abilityOverride": ""
      }
    ],
    "DIKDGEMENBA": {
      "lifeTime": 3.5
    },
    "move": {
      "$type": "DCNGIEDOJBG",
      "speed": 30.0,
      "maxSpeed": 30.0,
      "minSpeed": 8.0,
      "AOHCALMCNHB": 1.0,
      "ELPIEGMDKFC": true
    },
    "EHLHLJKBBBN": {
      "$type": "CBHLADGGJNA",
      "collision": {
        "targetType": "Enemy"
      },
      "EJIHDAJIDGP": [
        {
          "$type": "FPMCAJNLEEK",
          "abilityName": "Avatar_Klee_ElementalBurst_CreateFunnel"
        }
      ]
    }
  },
  "Klee_ExtraAttack": {
    "$type": "DIPBMCMACLG",
    "common": {
      "effectAttachShape": {
        "$type": "GGMDGIIFNHF"
      },
      "checkInSurface": true
    },
    "combat": {
      "property": {
        "useCreatorProperty": true,
        "weight": 150.0,
        "isLockHP": true,
        "isGhostToEnemy": true
      },
      "combatLock": {
        "lockShape": "CircleLockEnemy",
        "denyLockOn": true,
        "lockType": "Gadget_Lv1"
      },
      "die": {
        "dieDisappearEffect": "Eff_Klee_ExtraAttack_Clover_Die"
      }
    },
    "combatTemplate": "",
    "abilities": [
      {
        "abilityID": "Material",
        "abilityName": "Avatar_Klee_ExtraAttack_Clover",
        "abilityOverride": ""
      }
    ],
    "DIKDGEMENBA": {
      "lifeTime": 1.3200000524520874
    },
    "stateLayers": {
      "defaultLayer": {
        "$type": "FAEOIIEHJEA",
        "FOBEKEFIAJD": "",
        "stateIDs": {
          "ExtraAttack": {
            "$type": "EHFKEKABDCB",
            "NIPCDPELLJI": {
              "ExtraAttack": [
                "Klee_ExtraAttack_Clover"
              ]
            },
            "KECBMDMPLNC": true
          }
        }
      }
    }
  },
  "Klee_ExtraAttack_Bullet": {
    "$type": "DIPBMCMACLG",
    "common": {
      "effectAttachShape": {
        "$type": "GGMDGIIFNHF"
      }
    },
    "combat": {
      "property": {
        "useCreatorProperty": true,
        "isGhostToAllied": true,
        "isGhostToEnemy": true,
        "MBEICKDJMFI": false
      },
      "beHit": {
        "hitBloodEffect": "",
        "IPPKADMAEPO": true,
        "muteAllHitEffect": true,
        "muteAllHitText": true
      },
      "combatLock": {
        "lockShape": "CircleLockEnemy",
        "denyLockOn": true,
        "lockType": "Gadget_Lv1"
      }
    },
    "combatTemplate": "",
    "abilities": [
      {
        "abilityID": "Material",
        "abilityName": "Avatar_Klee_ExtraAttack_Clover_Bullet",
        "abilityOverride": ""
      }
    ],
    "DIKDGEMENBA": {
      "lifeTime": 0.800000011920929
    },
    "move": {
      "$type": "DCNGIEDOJBG",
      "speed": 30.0,
      "maxSpeed": 45.0,
      "minSpeed": 10.0,
      "AOHCALMCNHB": 1.0,
      "CPOHOLCJKDA": 0.10000000149011612,
      "ELPIEGMDKFC": true
    },
    "EHLHLJKBBBN": {
      "$type": "CBHLADGGJNA",
      "collision": {
        "targetType": "Enemy"
      },
      "EJIHDAJIDGP": [
        {
          "$type": "FPMCAJNLEEK",
          "abilityName": "Avatar_Klee_ExtraAttack_Clover_Bullet"
        }
      ]
    }
  }
}
