{
  "PlayerBoy_Grass_SkillUpgrade_1": [
    {
      "$type": "HFFOGCCHAAG",
      "abilityName": "Avatar_PlayerBoy_NormalAttack_DamageHandler",
      "KKNFGEFFFLI": "NormalAttack_01_DamagePercentage",
      "EJMCFJFMIBC": "%1"
    },
    {
      "$type": "HFFOGCCHAAG",
      "abilityName": "Avatar_PlayerBoy_NormalAttack_DamageHandler",
      "KKNFGEFFFLI": "NormalAttack_02_DamagePercentage",
      "EJMCFJFMIBC": "%2"
    },
    {
      "$type": "HFFOGCCHAAG",
      "abilityName": "Avatar_PlayerBoy_NormalAttack_DamageHandler",
      "KKNFGEFFFLI": "NormalAttack_03_DamagePercentage",
      "EJMCFJFMIBC": "%3"
    },
    {
      "$type": "HFFOGCCHAAG",
      "abilityName": "Avatar_PlayerBoy_NormalAttack_DamageHandler",
      "KKNFGEFFFLI": "NormalAttack_04_DamagePercentage",
      "EJMCFJFMIBC": "%4"
    },
    {
      "$type": "HFFOGCCHAAG",
      "abilityName": "Avatar_PlayerBoy_NormalAttack_DamageHandler",
      "KKNFGEFFFLI": "NormalAttack_05_DamagePercentage",
      "EJMCFJFMIBC": "%5"
    },
    {
      "$type": "HFFOGCCHAAG",
      "abilityName": "Avatar_PlayerBoy_NormalAttack_DamageHandler",
      "KKNFGEFFFLI": "ExtraAttack_01_DamagePercentage",
      "EJMCFJFMIBC": "%6"
    },
    {
      "$type": "HFFOGCCHAAG",
      "abilityName": "Avatar_PlayerBoy_NormalAttack_DamageHandler",
      "KKNFGEFFFLI": "ExtraAttack_02_DamagePercentage",
      "EJMCFJFMIBC": "%7"
    },
    {
      "$type": "HFFOGCCHAAG",
      "abilityName": "Avatar_PlayerBoy_ExtraAttack_Grass",
      "KKNFGEFFFLI": "ExtraAttack_Sword_Stamina_Cost",
      "EJMCFJFMIBC": "%8"
    },
    {
      "$type": "HFFOGCCHAAG",
      "abilityName": "Avatar_PlayerBoy_FallingAnthem",
      "KKNFGEFFFLI": "FallingAnthem_Normal_Loop_Damage",
      "EJMCFJFMIBC": "%9"
    },
    {
      "$type": "HFFOGCCHAAG",
      "abilityName": "Avatar_PlayerBoy_FallingAnthem",
      "KKNFGEFFFLI": "FallingAnthem_Normal_Rank_1_Damage",
      "EJMCFJFMIBC": "%10"
    },
    {
      "$type": "HFFOGCCHAAG",
      "abilityName": "Avatar_PlayerBoy_FallingAnthem",
      "KKNFGEFFFLI": "FallingAnthem_Normal_Rank_2_Damage",
      "EJMCFJFMIBC": "%11"
    }
  ],
  "PlayerGirl_Grass_SkillUpgrade_1": [
    {
      "$type": "HFFOGCCHAAG",
      "abilityName": "Avatar_PlayerGirl_NormalAttack_DamageHandler",
      "KKNFGEFFFLI": "NormalAttack_01_DamagePercentage",
      "EJMCFJFMIBC": "%1"
    },
    {
      "$type": "HFFOGCCHAAG",
      "abilityName": "Avatar_PlayerGirl_NormalAttack_DamageHandler",
      "KKNFGEFFFLI": "NormalAttack_02_DamagePercentage",
      "EJMCFJFMIBC": "%2"
    },
    {
      "$type": "HFFOGCCHAAG",
      "abilityName": "Avatar_PlayerGirl_NormalAttack_DamageHandler",
      "KKNFGEFFFLI": "NormalAttack_03_DamagePercentage",
      "EJMCFJFMIBC": "%3"
    },
    {
      "$type": "HFFOGCCHAAG",
      "abilityName": "Avatar_PlayerGirl_NormalAttack_DamageHandler",
      "KKNFGEFFFLI": "NormalAttack_04_DamagePercentage",
      "EJMCFJFMIBC": "%4"
    },
    {
      "$type": "HFFOGCCHAAG",
      "abilityName": "Avatar_PlayerGirl_NormalAttack_DamageHandler",
      "KKNFGEFFFLI": "NormalAttack_05_DamagePercentage",
      "EJMCFJFMIBC": "%5"
    },
    {
      "$type": "HFFOGCCHAAG",
      "abilityName": "Avatar_PlayerGirl_NormalAttack_DamageHandler",
      "KKNFGEFFFLI": "ExtraAttack_01_DamagePercentage",
      "EJMCFJFMIBC": "%6"
    },
    {
      "$type": "HFFOGCCHAAG",
      "abilityName": "Avatar_PlayerGirl_NormalAttack_DamageHandler",
      "KKNFGEFFFLI": "ExtraAttack_02_DamagePercentage",
      "EJMCFJFMIBC": "%7"
    },
    {
      "$type": "HFFOGCCHAAG",
      "abilityName": "Avatar_PlayerGirl_ExtraAttack_Grass",
      "KKNFGEFFFLI": "ExtraAttack_Sword_Stamina_Cost",
      "EJMCFJFMIBC": "%8"
    },
    {
      "$type": "HFFOGCCHAAG",
      "abilityName": "Avatar_PlayerGirl_FallingAnthem",
      "KKNFGEFFFLI": "FallingAnthem_Normal_Loop_Damage",
      "EJMCFJFMIBC": "%9"
    },
    {
      "$type": "HFFOGCCHAAG",
      "abilityName": "Avatar_PlayerGirl_FallingAnthem",
      "KKNFGEFFFLI": "FallingAnthem_Normal_Rank_1_Damage",
      "EJMCFJFMIBC": "%10"
    },
    {
      "$type": "HFFOGCCHAAG",
      "abilityName": "Avatar_PlayerGirl_FallingAnthem",
      "KKNFGEFFFLI": "FallingAnthem_Normal_Rank_2_Damage",
      "EJMCFJFMIBC": "%11"
    }
  ],
  "Player_Grass_Constellation_1": [
    {
      "$type": "DDCCNFACEJL",
      "abilityName": "Avatar_PlayerBoy_ElementalArt_Grass",
      "DMDCKNEEKBN": "Player_Grass_ElementArt_Energy_Recover_Talent_1"
    },
    {
      "$type": "HFFOGCCHAAG",
      "abilityName": "Avatar_PlayerBoy_ElementalArt_Grass",
      "KKNFGEFFFLI": "Element_Recover_By_Talent_1",
      "EJMCFJFMIBC": "%1"
    }
  ],
  "Player_Grass_Constellation_2": [
    {
      "$type": "DDCCNFACEJL",
      "abilityName": "Avatar_Player_Grass_Seed_Gadget",
      "DMDCKNEEKBN": "Player_Grass_Seed_Prolong_Talent_2"
    },
    {
      "$type": "HFFOGCCHAAG",
      "abilityName": "Avatar_Player_Grass_Seed_Gadget",
      "KKNFGEFFFLI": "Grass_Seed_Duration",
      "EJMCFJFMIBC": "%1"
    }
  ],
  "Player_Grass_Constellation_3": [
    {
      "$type": "PJAKCFFNFHH",
      "PPNFDJBIIPO": "AvatarSkill",
      "BIMFGICKAME": 2,
      "KOGFGKHODPO": 3
    }
  ],
  "Player_Grass_Constellation_4": [
    {
      "$type": "DDCCNFACEJL",
      "abilityName": "Avatar_Player_Grass_Permanent_Skill_1",
      "DMDCKNEEKBN": "Player_Grass_Seed_Aura_Up_Talent_4"
    }
  ],
  "Player_Grass_Constellation_5": [
    {
      "$type": "PJAKCFFNFHH",
      "PPNFDJBIIPO": "AvatarSkill",
      "BIMFGICKAME": 9,
      "KOGFGKHODPO": 3
    }
  ],
  "Player_Grass_Constellation_6": [
    {
      "$type": "DDCCNFACEJL",
      "abilityName": "Avatar_Player_Grass_Permanent_Skill_1",
      "DMDCKNEEKBN": "Player_Grass_Seed_Aura_Extra_Talent_6"
    },
    {
      "$type": "HFFOGCCHAAG",
      "abilityName": "Avatar_Player_Grass_Permanent_Skill_1",
      "KKNFGEFFFLI": "Elemental_Damage_Up_Ratio",
      "EJMCFJFMIBC": "%1"
    }
  ],
  "Player_Grass_PermanentSkill_1": [
    {
      "$type": "DDCCNFACEJL",
      "abilityName": "Avatar_Player_Grass_Permanent_Skill_1",
      "DMDCKNEEKBN": "Player_Grass_Seed_Aura_Permanent_Skill_1"
    },
    {
      "$type": "HFFOGCCHAAG",
      "abilityName": "Avatar_Player_Grass_Permanent_Skill_1",
      "KKNFGEFFFLI": "Grass_Seed_Element_Mastery_Up",
      "EJMCFJFMIBC": "%1"
    }
  ],
  "Player_Grass_PermanentSkill_2": [
    {
      "$type": "KBHIMCFOOEA",
      "abilityName": "Avatar_Player_Grass_Damage_Up_By_Element_Mastery"
    },
    {
      "$type": "HFFOGCCHAAG",
      "abilityName": "Avatar_Player_Grass_Damage_Up_By_Element_Mastery",
      "KKNFGEFFFLI": "Element_Mastery_Transform_To_ElementArt_Damage_Ratio",
      "EJMCFJFMIBC": "%1"
    },
    {
      "$type": "HFFOGCCHAAG",
      "abilityName": "Avatar_Player_Grass_Damage_Up_By_Element_Mastery",
      "KKNFGEFFFLI": "Element_Mastery_Transform_To_ElementBurst_Damage_Ratio",
      "EJMCFJFMIBC": "%2"
    }
  ],
  "Player_Grass_SkillUpgrade_1": [
    {
      "$type": "HFFOGCCHAAG",
      "abilityName": "Avatar_PlayerBoy_ElementalArt_Grass",
      "KKNFGEFFFLI": "ElementArt_Damage",
      "EJMCFJFMIBC": "%1"
    }
  ],
  "Player_Grass_SkillUpgrade_2": [
    {
      "$type": "HFFOGCCHAAG",
      "abilityName": "Avatar_Player_Grass_Seed_Gadget",
      "KKNFGEFFFLI": "Grass_Seed_Damage_Ratio",
      "EJMCFJFMIBC": "%1"
    },
    {
      "$type": "HFFOGCCHAAG",
      "abilityName": "Avatar_Player_Grass_Seed_Gadget",
      "KKNFGEFFFLI": "Grass_Seed_Fire_Boom_Ratio",
      "EJMCFJFMIBC": "%2"
    },
    {
      "$type": "HFFOGCCHAAG",
      "abilityName": "Avatar_Player_Grass_Seed_Gadget",
      "KKNFGEFFFLI": "Grass_Seed_Duration",
      "EJMCFJFMIBC": "%5"
    }
  ]
}
