{
  "Qin_ProudSkill_1": [
    {
      "$type": "HFFOGCCHAAG",
      "abilityName": "Avatar_Qin_NormalAttackDamage",
      "KKNFGEFFFLI": "Attack01",
      "EJMCFJFMIBC": "%1"
    },
    {
      "$type": "HFFOGCCHAAG",
      "abilityName": "Avatar_Qin_NormalAttackDamage",
      "KKNFGEFFFLI": "Attack02",
      "EJMCFJFMIBC": "%2"
    },
    {
      "$type": "HFFOGCCHAAG",
      "abilityName": "Avatar_Qin_NormalAttackDamage",
      "KKNFGEFFFLI": "Attack03",
      "EJMCFJFMIBC": "%3"
    },
    {
      "$type": "HFFOGCCHAAG",
      "abilityName": "Avatar_Qin_NormalAttackDamage",
      "KKNFGEFFFLI": "Attack04",
      "EJMCFJFMIBC": "%4"
    },
    {
      "$type": "HFFOGCCHAAG",
      "abilityName": "Avatar_Qin_NormalAttackDamage",
      "KKNFGEFFFLI": "Attack05",
      "EJMCFJFMIBC": "%5"
    },
    {
      "$type": "HFFOGCCHAAG",
      "abilityName": "Avatar_Qin_NormalAttackDamage",
      "KKNFGEFFFLI": "ExtraAttack",
      "EJMCFJFMIBC": "%6"
    },
    {
      "$type": "HFFOGCCHAAG",
      "abilityName": "Avatar_Qin_ExtraAttack",
      "KKNFGEFFFLI": "ExtraAttack_Sword_Stamina_Cost",
      "EJMCFJFMIBC": "%7"
    },
    {
      "$type": "HFFOGCCHAAG",
      "abilityName": "Avatar_Qin_FallingAnthem",
      "KKNFGEFFFLI": "FallingAnthem_Normal_Loop_Damage",
      "EJMCFJFMIBC": "%8"
    },
    {
      "$type": "HFFOGCCHAAG",
      "abilityName": "Avatar_Qin_FallingAnthem",
      "KKNFGEFFFLI": "FallingAnthem_Normal_Rank_1_Damage",
      "EJMCFJFMIBC": "%9"
    },
    {
      "$type": "HFFOGCCHAAG",
      "abilityName": "Avatar_Qin_FallingAnthem",
      "KKNFGEFFFLI": "FallingAnthem_Normal_Rank_2_Damage",
      "EJMCFJFMIBC": "%10"
    }
  ],
  "Qin_ProudSkill_2": [
    {
      "$type": "HFFOGCCHAAG",
      "abilityName": "Avatar_Qin_VortexSmash",
      "KKNFGEFFFLI": "Art_DMG",
      "EJMCFJFMIBC": "%1"
    },
    {
      "$type": "HFFOGCCHAAG",
      "abilityName": "Avatar_Qin_VortexSmash",
      "KKNFGEFFFLI": "StaminaCost",
      "EJMCFJFMIBC": "%2"
    }
  ],
  "Qin_ProudSkill_3": [
    {
      "$type": "HFFOGCCHAAG",
      "abilityName": "Avatar_Qin_DandelionWind_Push",
      "KKNFGEFFFLI": "Burst_DMG",
      "EJMCFJFMIBC": "%1"
    },
    {
      "$type": "HFFOGCCHAAG",
      "abilityName": "Avatar_Qin_DandelionWind_Harm",
      "KKNFGEFFFLI": "InOutHarm",
      "EJMCFJFMIBC": "%2"
    },
    {
      "$type": "HFFOGCCHAAG",
      "abilityName": "Avatar_Qin_DandelionWind_Heal",
      "KKNFGEFFFLI": "BurstHeal",
      "EJMCFJFMIBC": "%3"
    },
    {
      "$type": "HFFOGCCHAAG",
      "abilityName": "Avatar_Qin_DandelionWind_Heal",
      "KKNFGEFFFLI": "BurstHealConst",
      "EJMCFJFMIBC": "%4"
    },
    {
      "$type": "HFFOGCCHAAG",
      "abilityName": "Avatar_Qin_DandelionWind_Heal",
      "KKNFGEFFFLI": "Heal",
      "EJMCFJFMIBC": "%5"
    },
    {
      "$type": "HFFOGCCHAAG",
      "abilityName": "Avatar_Qin_DandelionWind_Heal",
      "KKNFGEFFFLI": "HealConst",
      "EJMCFJFMIBC": "%6"
    }
  ],
  "Qin_ProudSkill_Private1": [
    {
      "$type": "KBHIMCFOOEA",
      "abilityName": "Avatar_Qin_AttackCritic"
    },
    {
      "$type": "HFFOGCCHAAG",
      "abilityName": "Avatar_Qin_AttackCritic",
      "KKNFGEFFFLI": "Chance",
      "EJMCFJFMIBC": "%1"
    },
    {
      "$type": "HFFOGCCHAAG",
      "abilityName": "Avatar_Qin_AttackCritic",
      "KKNFGEFFFLI": "HealByAttack",
      "EJMCFJFMIBC": "%2"
    }
  ],
  "Qin_ProudSkill_Private2": [
    {
      "$type": "DDCCNFACEJL",
      "abilityName": "Avatar_Qin_DandelionWind",
      "DMDCKNEEKBN": "RestoreEnergy"
    },
    {
      "$type": "HFFOGCCHAAG",
      "abilityName": "Avatar_Qin_DandelionWind",
      "KKNFGEFFFLI": "Rate",
      "EJMCFJFMIBC": "%1"
    }
  ],
  "Qin_Talent_1": [
    {
      "$type": "DDCCNFACEJL",
      "abilityName": "Avatar_Qin_VortexSmash",
      "DMDCKNEEKBN": "Stronger_VortexSmash"
    },
    {
      "$type": "HFFOGCCHAAG",
      "abilityName": "Avatar_Qin_VortexSmash",
      "KKNFGEFFFLI": "DamageRate",
      "EJMCFJFMIBC": "%1"
    }
  ],
  "Qin_Talent_2": [
    {
      "$type": "KBHIMCFOOEA",
      "abilityName": "Avatar_Qin_TeamSpeedWhenGetElementBall"
    },
    {
      "$type": "HFFOGCCHAAG",
      "abilityName": "Avatar_Qin_TeamSpeedWhenGetElementBall",
      "KKNFGEFFFLI": "AtkSpeed",
      "EJMCFJFMIBC": "%1"
    },
    {
      "$type": "HFFOGCCHAAG",
      "abilityName": "Avatar_Qin_TeamSpeedWhenGetElementBall",
      "KKNFGEFFFLI": "Speed",
      "EJMCFJFMIBC": "%2"
    },
    {
      "$type": "HFFOGCCHAAG",
      "abilityName": "Avatar_Qin_TeamSpeedWhenGetElementBall",
      "KKNFGEFFFLI": "Time",
      "EJMCFJFMIBC": "%3"
    }
  ],
  "Qin_Talent_3": [
    {
      "$type": "PJAKCFFNFHH",
      "PPNFDJBIIPO": "AvatarSkill",
      "BIMFGICKAME": 9,
      "KOGFGKHODPO": 3
    }
  ],
  "Qin_Talent_4": [
    {
      "$type": "DDCCNFACEJL",
      "abilityName": "Avatar_Qin_DandelionWind_Heal",
      "DMDCKNEEKBN": "WindPressure"
    },
    {
      "$type": "HFFOGCCHAAG",
      "abilityName": "Avatar_Qin_DandelionWind_Heal",
      "KKNFGEFFFLI": "WindHurt",
      "EJMCFJFMIBC": "-%1"
    }
  ],
  "Qin_Talent_5": [
    {
      "$type": "PJAKCFFNFHH",
      "PPNFDJBIIPO": "AvatarSkill",
      "BIMFGICKAME": 2,
      "KOGFGKHODPO": 3
    }
  ],
  "Qin_Talent_6": [
    {
      "$type": "DDCCNFACEJL",
      "abilityName": "Avatar_Qin_DandelionWind_Heal",
      "DMDCKNEEKBN": "WindShield"
    },
    {
      "$type": "HFFOGCCHAAG",
      "abilityName": "Avatar_Qin_DandelionWind_Heal",
      "KKNFGEFFFLI": "LessHurt",
      "EJMCFJFMIBC": "%1"
    }
  ]
}
